Xaunsurn/__init__.py
Xaunsurn/main.py
Xaunsurn-0.1.1.dist-info/METADATA
Xaunsurn-0.1.1.dist-info/WHEEL
Xaunsurn-0.1.1.dist-info/entry_points.txt
Xaunsurn-0.1.1.dist-info/top_level.txt
Xaunsurn-0.1.1.dist-info/RECORD
